{
  "generatedAt": "2026-05-05T11:06:53.108Z",
  "source": "github-actions-coinbase-rest-snapshot",
  "prices": {
    "oil": {
      "id": "oil",
      "ticker": "NOL-18MAY26-CDE",
      "productId": "NOL-18MAY26-CDE",
      "productType": "Coinbase futures contract",
      "fetchedAt": "2026-05-05T11:06:52.882Z",
      "minimumTradeValue": 104.78999999999999,
      "ok": true,
      "price": 104.78999999999999,
      "bestBid": 104.77,
      "bestAsk": 104.81,
      "lastTrade": 104.73,
      "method": "bid_ask_midpoint"
    },
    "natural-gas": {
      "id": "natural-gas",
      "ticker": "NG reference",
      "productId": "NATURAL-GAS-USD",
      "productType": "Reference price, not a listed Coinbase futures contract",
      "fetchedAt": "2026-05-05T11:06:52.945Z",
      "minimumTradeValue": null,
      "ok": false,
      "price": null,
      "error": "404 Not Found",
      "method": "unavailable"
    },
    "gold": {
      "id": "gold",
      "ticker": "Gold reference",
      "productId": "GOLD-USD",
      "productType": "Reference price, not a listed Coinbase futures contract",
      "fetchedAt": "2026-05-05T11:06:52.947Z",
      "minimumTradeValue": null,
      "ok": false,
      "price": null,
      "error": "404 Not Found",
      "method": "unavailable"
    },
    "silver": {
      "id": "silver",
      "ticker": "Silver reference",
      "productId": "SILVER-USD",
      "productType": "Reference price, not a listed Coinbase futures contract",
      "fetchedAt": "2026-05-05T11:06:52.947Z",
      "minimumTradeValue": null,
      "ok": false,
      "price": null,
      "error": "404 Not Found",
      "method": "unavailable"
    },
    "copper": {
      "id": "copper",
      "ticker": "Copper reference",
      "productId": "COPPER-USD",
      "productType": "Reference price, not a listed Coinbase futures contract",
      "fetchedAt": "2026-05-05T11:06:52.948Z",
      "minimumTradeValue": null,
      "ok": false,
      "price": null,
      "error": "404 Not Found",
      "method": "unavailable"
    },
    "platinum": {
      "id": "platinum",
      "ticker": "Platinum reference",
      "productId": "PLATINUM-USD",
      "productType": "Reference price, not a listed Coinbase futures contract",
      "fetchedAt": "2026-05-05T11:06:52.949Z",
      "minimumTradeValue": null,
      "ok": false,
      "price": null,
      "error": "404 Not Found",
      "method": "unavailable"
    }
  }
}
